majime/__init__.py
majime/__main__.py
majime-0.0.10.dist-info/METADATA
majime-0.0.10.dist-info/WHEEL
majime-0.0.10.dist-info/entry_points.txt
majime-0.0.10.dist-info/top_level.txt
majime-0.0.10.dist-info/RECORD
