Metadata-Version: 2.1
Name: majime
Version: 0.0.10
Summary: Dead Simple API Unit Tests
Home-page: https://github.com/u1i/majime
Author: Uli Hitzel
Author-email: uli.hitzel@gmail.com
License: UNKNOWN
Platform: UNKNOWN
Classifier: Programming Language :: Python :: 3
Classifier: License :: OSI Approved :: MIT License
Classifier: Operating System :: OS Independent
Requires-Dist: requests
Requires-Dist: pyyaml
Requires-Dist: termcolor
